axshll/__init__.py
axshll-0.0.1.dist-info/LICENSE
axshll-0.0.1.dist-info/METADATA
axshll-0.0.1.dist-info/WHEEL
axshll-0.0.1.dist-info/top_level.txt
axshll-0.0.1.dist-info/RECORD
