Metadata-Version: 2.1
Name: axshll
Version: 0.0.1
Summary: xshll
Author: xxsaf
License: MIT
License-File: LICENSE
